{
  "main": {
    "id": "69418d7ea6aabd56",
    "type": "split",
    "children": [
      {
        "id": "bd295ca619a972cc",
        "type": "tabs",
        "children": [
          {
            "id": "fc52198744952495",
            "type": "leaf",
            "state": {
              "type": "markdown",
              "state": {
                "file": "design/concepts/Comprehensive Design File.md",
                "mode": "source",
                "source": false
              },
              "icon": "lucide-file",
              "title": "Comprehensive Design File"
            }
          }
        ]
      }
    ],
    "direction": "vertical"
  },
  "left": {
    "id": "ec24c9d8c578d7c4",
    "type": "split",
    "children": [
      {
        "id": "4734149109f01b21",
        "type": "tabs",
        "children": [
          {
            "id": "9b42b4503c7d88ad",
            "type": "leaf",
            "state": {
              "type": "file-explorer",
              "state": {
                "sortOrder": "alphabetical",
                "autoReveal": false
              },
              "icon": "lucide-folder-closed",
              "title": "Files"
            }
          },
          {
            "id": "91b6b6a68ddda469",
            "type": "leaf",
            "state": {
              "type": "search",
              "state": {
                "query": "",
                "matchingCase": false,
                "explainSearch": false,
                "collapseAll": false,
                "extraContext": false,
                "sortOrder": "alphabetical"
              },
              "icon": "lucide-search",
              "title": "Search"
            }
          },
          {
            "id": "dd33aa2dc5ea9444",
            "type": "leaf",
            "state": {
              "type": "bookmarks",
              "state": {},
              "icon": "lucide-bookmark",
              "title": "Bookmarks"
            }
          }
        ]
      }
    ],
    "direction": "horizontal",
    "width": 300
  },
  "right": {
    "id": "ffc60e9763cc384c",
    "type": "split",
    "children": [
      {
        "id": "d3c060c350ac362f",
        "type": "tabs",
        "children": [
          {
            "id": "a3cf4594c06125f1",
            "type": "leaf",
            "state": {
              "type": "backlink",
              "state": {
                "file": "README.md",
                "collapseAll": false,
                "extraContext": false,
                "sortOrder": "alphabetical",
                "showSearch": false,
                "searchQuery": "",
                "backlinkCollapsed": false,
                "unlinkedCollapsed": true
              },
              "icon": "links-coming-in",
              "title": "Backlinks for README"
            }
          },
          {
            "id": "5954b06acde07646",
            "type": "leaf",
            "state": {
              "type": "outgoing-link",
              "state": {
                "file": "README.md",
                "linksCollapsed": false,
                "unlinkedCollapsed": true
              },
              "icon": "links-going-out",
              "title": "Outgoing links from README"
            }
          },
          {
            "id": "bb5529fce9138644",
            "type": "leaf",
            "state": {
              "type": "tag",
              "state": {
                "sortOrder": "frequency",
                "useHierarchy": true,
                "showSearch": false,
                "searchQuery": ""
              },
              "icon": "lucide-tags",
              "title": "Tags"
            }
          },
          {
            "id": "0632f167ef7438ee",
            "type": "leaf",
            "state": {
              "type": "outline",
              "state": {
                "file": "README.md",
                "followCursor": false,
                "showSearch": false,
                "searchQuery": ""
              },
              "icon": "lucide-list",
              "title": "Outline of README"
            }
          }
        ]
      }
    ],
    "direction": "horizontal",
    "width": 300,
    "collapsed": true
  },
  "left-ribbon": {
    "hiddenItems": {
      "switcher:Open quick switcher": false,
      "graph:Open graph view": false,
      "canvas:Create new canvas": false,
      "daily-notes:Open today's daily note": false,
      "templates:Insert template": false,
      "command-palette:Open command palette": false,
      "bases:Create new base": false
    }
  },
  "active": "fc52198744952495",
  "lastOpenFiles": [
    "design/api-spec.md",
    "scripts/seed_intents.ts",
    "design/tools/api-extraction-from-spec.md",
    "context/design/tools/api-extraction-from-spec.md/20251021_185957.70c5d2f8.md",
    "context/design/tools/api-extraction-from-spec.md/steps/API Specification.e73bd34d.md",
    "context/design/tools/api-extraction-from-spec.md/20251021_185926.b7383036.md",
    "context/design/tools/api-extraction-from-spec.md/steps/concept.324fee2b.md",
    "design/concepts/Resource/Resource.md",
    "design/concepts/ResourceIntent/ResourceIntent.md",
    "design/concepts/ResourceIntent/design-file.md",
    "design/concepts/Resource/design-file.md",
    "design/concepts/Resource/prompts/test-prompt.md",
    "design/concepts/Resource/prompts/implementation-prompt.md",
    "context/design/concepts/Resource/Resource.md/20251021_184721.156b9e68.md",
    "context/design/concepts/Resource/Resource.md/steps/response.ec502540.md",
    "context/design/concepts/Resource/Resource.md/steps/concept.a6f29971.md",
    "context/design/concepts/Resource/Resource.md/steps",
    "context/design/concepts/Resource/Resource.md/20251021_184716.f41e8183.md",
    "context/design/concepts/Resource/Resource.md",
    "design/concepts/ResourceStatus/ResourceStatus.md",
    "context/design/tools/api-extraction-from-spec.md/20251021_143058.245fc338.md",
    "context/design/tools/api-extraction-from-spec.md/steps/API Specification.c9efb4e3.md",
    "context/design/tools/api-extraction-from-spec.md/20251021_143043.4f83bede.md",
    "context/design/tools/api-extraction-from-spec.md/steps/concept.d14f7cb4.md",
    "design/concepts/Comprehensive Design File.md",
    "design/concepts/ResourceIntent/prompts/test-prompt.md",
    "src/concepts/ResourceIntent/test-output.md",
    "src/concepts/ResourceIntent/ResourceIntent.test.ts",
    "context/design/concepts/ResourceIntent/prompts/test-prompt.md/steps",
    "src/concepts/ResourceIntent/ResourceIntent.ts",
    "src/concepts/ResourceIntent",
    "context/design/concepts/ResourceIntent/prompts/implementation-prompt.md/steps",
    "context/deno.json",
    "context/design/concepts/ResourceIntent/prompts/concept-prompt.md/steps",
    "context/design/concepts/ResourceIntent/prompts"
  ]
}